StellarLog/StellarLog.py
StellarLog/__init__.py
StellarLog-0.0.9.dist-info/LICENSE
StellarLog-0.0.9.dist-info/METADATA
StellarLog-0.0.9.dist-info/WHEEL
StellarLog-0.0.9.dist-info/top_level.txt
StellarLog-0.0.9.dist-info/RECORD
