Metadata-Version: 2.1
Name: StellarLog
Version: 0.0.9
Summary: A Lib for Easy Logging
Home-page: https://github.com/powerfulbean/StellarLog
Author: Powerfulbean
Author-email: powerfulbean@gmail.com
License: UNKNOWN
Platform: UNKNOWN
Classifier: Programming Language :: Python :: 3
Classifier: License :: OSI Approved :: MIT License
Classifier: Operating System :: OS Independent
